echo/__init__.py
echo/__main__.py
echo/api/__init__.py
echo/api/routers/chat.py
echo/api/routers/plugins.py
echo/api/routers/system.py
echo/api/routes.py
echo/api/schemas.py
echo/api/services.py
echo/cli.py
echo/config/__init__.py
echo/config/settings.py
echo/core/__init__.py
echo/core/orchestrator/__init__.py
echo/core/orchestrator/coordinator.py
echo/core/orchestrator/state.py
echo/core/services/__init__.py
echo/core/services/conversation_service.py
echo/core/services/orchestrator_service.py
echo/core/services/service_container.py
echo/domain/__init__.py
echo/domain/dtos/__init__.py
echo/domain/dtos/analytics_dtos.py
echo/domain/dtos/chat_dtos.py
echo/domain/dtos/thread_dtos.py
echo/domain/models/__init__.py
echo/domain/models/conversation.py
echo/domain/models/organization.py
echo/domain/models/thread.py
echo/domain/models/user.py
echo/infrastructure/__init__.py
echo/infrastructure/database/__init__.py
echo/infrastructure/database/connection.py
echo/infrastructure/database/factory.py
echo/infrastructure/database/models/__init__.py
echo/infrastructure/database/models/base.py
echo/infrastructure/database/models/conversation.py
echo/infrastructure/database/models/organization.py
echo/infrastructure/database/models/thread.py
echo/infrastructure/database/models/user.py
echo/infrastructure/database/repositories/__init__.py
echo/infrastructure/database/repositories/cassandra/__init__.py
echo/infrastructure/database/repositories/cassandra/cassandra_repositories.py
echo/infrastructure/database/repositories/conversation_repository.py
echo/infrastructure/database/repositories/mariadb/__init__.py
echo/infrastructure/database/repositories/mariadb/mariadb_repositories.py
echo/infrastructure/database/repositories/mongo/__init__.py
echo/infrastructure/database/repositories/mongo/mongo_repositories.py
echo/infrastructure/database/repositories/postgres/__init__.py
echo/infrastructure/database/repositories/postgres/postgresql_repositories.py
echo_app-1.0.2.dist-info/LICENSE
echo_app-1.0.2.dist-info/METADATA
echo_app-1.0.2.dist-info/WHEEL
echo_app-1.0.2.dist-info/entry_points.txt
echo_app-1.0.2.dist-info/RECORD
